starbot_message/__init__.py
starbot_message/core/__init__.py
starbot_message/core/dispatcher.py
starbot_message/core/event.py
starbot_message/core/handler.py
starbot_message/core/model.py
starbot_message-0.0.1b0.dist-info/LICENSE
starbot_message-0.0.1b0.dist-info/METADATA
starbot_message-0.0.1b0.dist-info/WHEEL
starbot_message-0.0.1b0.dist-info/RECORD
