Metadata-Version: 2.1
Name: starbot-message
Version: 0.0.1b0
Summary: StarBot 消息推送接口
Home-page: https://github.com/Starlwr/StarBotMessage
License: AGPL-3.0-only
Keywords: starbot,bilibili,bot
Author: Starlwr
Author-email: lwr1104@qq.com
Requires-Python: >=3.10,<4.0
Classifier: License :: OSI Approved :: GNU Affero General Public License v3
Classifier: Programming Language :: Python :: 3
Classifier: Programming Language :: Python :: 3.10
Classifier: Programming Language :: Python :: 3.11
Requires-Dist: aiohttp (>=3.9.3,<4.0.0)
Requires-Dist: loguru (>=0.7.2,<0.8.0)
Requires-Dist: starbot-executor (>=1.3.0,<2.0.0)
Project-URL: Repository, https://github.com/Starlwr/StarBotMessage
